pomodorotk/__init__.py
pomodorotk/pomodoro.py
pomodorotk/resources/__init__.py
pomodorotk/resources/alarm.mp3
pomodorotk/resources/tomato.png
pomodorotk/resources/tomato_dis.png
pomodorotk/resources/tomato_progress.png
pomodorotk/task.py
pomodorotk/tasks_frame.py
pomodorotk-0.1.1.dist-info/METADATA
pomodorotk-0.1.1.dist-info/WHEEL
pomodorotk-0.1.1.dist-info/entry_points.txt
pomodorotk-0.1.1.dist-info/RECORD
