Metadata-Version: 2.1
Name: pomodorotk
Version: 0.1.1
Summary: 
Author: Fernando López
Author-email: fernando.e.lopez@gmail.com
Requires-Python: >=3.11,<4.0
Classifier: Programming Language :: Python :: 3
Classifier: Programming Language :: Python :: 3.11
Requires-Dist: ffmpeg-python (>=0.2.0,<0.3.0)
Requires-Dist: pydub (>=0.25.1,<0.26.0)
